setup.cfg
setup.py
bin/nosepicker
nosepicker/__init__.py
nosepicker/log.py
nosepicker/parser.py
nosepicker/shell.py
nosepicker.egg-info/PKG-INFO
nosepicker.egg-info/SOURCES.txt
nosepicker.egg-info/dependency_links.txt
nosepicker.egg-info/requires.txt
nosepicker.egg-info/top_level.txt