Metadata-Version: 1.0
Name: nosepicker
Version: 1.0.3
Summary: Scripts to parse nose xunit XML output files
Home-page: https://github.com/hile/nosepicker
Author: Ilkka Tuohela
Author-email: hile@iki.fi
License: PSF
Keywords: nose xunit output parser
Platform: UNKNOWN
